cehuibaibaoxiang.py
cehuibaibaoxiang-0.1.4.dist-info/licenses/license.txt
cehuibaibaoxiang-0.1.4.dist-info/METADATA
cehuibaibaoxiang-0.1.4.dist-info/WHEEL
cehuibaibaoxiang-0.1.4.dist-info/top_level.txt
cehuibaibaoxiang-0.1.4.dist-info/RECORD
