Metadata-Version: 2.4
Name: cehuibaibaoxiang
Version: 0.1.4
Summary: （自用）本人写的测绘专业课作业代码合集
Home-page: https://github.com/piaopiaoxuruop/cehuibaibaoxiang/tree/main?tab=readme-ov-file
Author: 徐若朴
Author-email: 2253959@tongji.edu.cn
License: MIT
Classifier: Programming Language :: Python :: 3
Classifier: License :: OSI Approved :: MIT License
Classifier: Operating System :: OS Independent
Classifier: Intended Audience :: Science/Research
Classifier: Topic :: Scientific/Engineering :: GIS
Requires-Python: >=3.8
License-File: license.txt
Requires-Dist: numpy
Requires-Dist: scipy
Requires-Dist: matplotlib
Requires-Dist: shapely
Requires-Dist: pyproj
Requires-Dist: rasterio
Requires-Dist: imageio
Requires-Dist: gdal
Requires-Dist: opencv-python
Requires-Dist: pandas
Dynamic: author
Dynamic: author-email
Dynamic: classifier
Dynamic: description
Dynamic: description-content-type
Dynamic: home-page
Dynamic: license
Dynamic: license-file
Dynamic: requires-dist
Dynamic: requires-python
Dynamic: summary
